hashime/__init__.py
hashime/__main__.py
hashime/__version__.py
hashime/algorithm.py
hashime/drunken_bishop.py
hashime/util.py
hashime-0.2.0.dist-info/METADATA
hashime-0.2.0.dist-info/WHEEL
hashime-0.2.0.dist-info/entry_points.txt
hashime-0.2.0.dist-info/licenses/LICENSE
hashime-0.2.0.dist-info/RECORD
