Metadata-Version: 2.4
Name: hashime
Version: 0.2.0
Summary: hash visualization tool
Project-URL: Homepage, https://github.com/sakhezech/hashime
License-Expression: MIT
License-File: LICENSE
Provides-Extra: dev
Requires-Dist: faterunner; extra == 'dev'
Requires-Dist: pytest; extra == 'dev'
Requires-Dist: ruff; extra == 'dev'
